dependency_injector/containers.pxd
dependency_injector/containers.cpython-310-aarch64-linux-gnu.so
dependency_injector/containers.pyi
dependency_injector/__init__.pyi
dependency_injector/errors.py
dependency_injector/wiring.py
dependency_injector/resources.py
dependency_injector/providers.pxd
dependency_injector/providers.cpython-310-aarch64-linux-gnu.so
dependency_injector/_cwiring.cpython-310-aarch64-linux-gnu.so
dependency_injector/providers.pyi
dependency_injector/__init__.py
dependency_injector/schema.py
dependency_injector/py.typed
dependency_injector/ext/aiohttp.py
dependency_injector/ext/__init__.pyi
dependency_injector/ext/flask.py
dependency_injector/ext/flask.pyi
dependency_injector/ext/__init__.py
dependency_injector/ext/aiohttp.pyi
dependency_injector2-4.41.1.dist-info/METADATA
dependency_injector2-4.41.1.dist-info/top_level.txt
dependency_injector2-4.41.1.dist-info/WHEEL
dependency_injector2-4.41.1.dist-info/RECORD
dependency_injector2-4.41.1.dist-info/LICENSE.rst
dependency_injector2-4.41.1.dist-info/zip-safe
